src/CONFIG_README.md
src/__init__.py
src/audit.py
src/config.py
src/config_watcher.py
src/gateway.py
src/main.py
src/metrics.py
src/middleware.py
src/policy.py
src/proxy.py
src/config/.mcp-gateway-rules.json.example
src/config/.mcp.json.example
agent_mcp_gateway-0.2.4.dist-info/METADATA
agent_mcp_gateway-0.2.4.dist-info/WHEEL
agent_mcp_gateway-0.2.4.dist-info/entry_points.txt
agent_mcp_gateway-0.2.4.dist-info/licenses/LICENSE
agent_mcp_gateway-0.2.4.dist-info/RECORD
