Metadata-Version: 2.4
Name: agent-mcp-gateway
Version: 0.2.4
Summary: An MCP gateway that aggregates your existing MCP servers and lets you define which servers and individual tools each agent or subagent can access. Solves Claude Code's MCP context window waste where all tool definitions load upfront instead of being discovered when actually needed.
Project-URL: Homepage, https://github.com/roddutra/agent-mcp-gateway
Project-URL: Documentation, https://github.com/roddutra/agent-mcp-gateway#readme
Project-URL: Repository, https://github.com/roddutra/agent-mcp-gateway
Project-URL: Issues, https://github.com/roddutra/agent-mcp-gateway/issues
Author: Rodrigo Franken Dutra
License: MIT
License-File: LICENSE
Keywords: agent,fastmcp,gateway,mcp,model-context-protocol,proxy
Classifier: Development Status :: 4 - Beta
Classifier: Intended Audience :: Developers
Classifier: License :: OSI Approved :: MIT License
Classifier: Programming Language :: Python :: 3
Classifier: Programming Language :: Python :: 3.12
Classifier: Topic :: Software Development :: Libraries :: Python Modules
Requires-Python: >=3.12
Requires-Dist: fastmcp<3.0,>=2.13.0.1
Requires-Dist: watchdog<7.0,>=6.0.0
